mjml.libs/libgcc_s-39080030.so.1
mjml/__init__.py
mjml/__init__.pyi
mjml/mjml.abi3.so
mjml/py.typed
mjml_python-1.3.6.dist-info/METADATA
mjml_python-1.3.6.dist-info/WHEEL
mjml_python-1.3.6.dist-info/licenses/LICENSE
mjml_python-1.3.6.dist-info/RECORD
