Metadata-Version: 2.4
Name: mjml-python
Version: 1.3.6
Classifier: Programming Language :: Rust
Classifier: Programming Language :: Python :: Implementation :: CPython
Classifier: Programming Language :: Python :: Implementation :: PyPy
Classifier: License :: OSI Approved :: MIT License
License-File: LICENSE
Summary: A Python wrapper for MRML (Rust port of MJML).
Requires-Python: >=3.7
Project-URL: Homepage, https://github.com/mgd020/mjml-python
Project-URL: Bug Tracker, https://github.com/mgd020/mjml-python/issues
